fluidattacks_connection_manager/__init__.py
fluidattacks_connection_manager/_common.py
fluidattacks_connection_manager/_utils.py
fluidattacks_connection_manager/py.typed
fluidattacks_connection_manager/_connection/__init__.py
fluidattacks_connection_manager/_connection/_core.py
fluidattacks_connection_manager/_connection/_setup.py
fluidattacks_connection_manager-3.0.0.dist-info/WHEEL
fluidattacks_connection_manager-3.0.0.dist-info/METADATA
fluidattacks_connection_manager-3.0.0.dist-info/RECORD
