Metadata-Version: 2.4
Name: fluidattacks_connection_manager
Version: 3.0.0
Summary: Common connection utils
Author-email: Product Team <development@fluidattacks.com>
Requires-Python: >=3.11
Classifier: License :: OSI Approved :: MIT License
Requires-Dist: fa-purity >=2.1.0, <3.0.0
Requires-Dist: fluidattacks-etl-utils >=3.0.0, <4.0.0
Requires-Dist: redshift-client >=9.0.0, <10.0.0
Requires-Dist: snowflake-client >=4.0.0, <5.0.0
